cvecli/__init__.py
cvecli/constants.py
cvecli/exceptions.py
cvecli/logging_config.py
cvecli/py.typed
cvecli/cli/__init__.py
cvecli/cli/main.py
cvecli/cli/commands/__init__.py
cvecli/cli/commands/db.py
cvecli/cli/commands/get.py
cvecli/cli/commands/products.py
cvecli/cli/commands/search.py
cvecli/cli/commands/stats.py
cvecli/cli/formatters/__init__.py
cvecli/cli/formatters/base.py
cvecli/cli/formatters/json_formatter.py
cvecli/cli/formatters/markdown_formatter.py
cvecli/cli/formatters/output.py
cvecli/cli/formatters/table_formatter.py
cvecli/core/__init__.py
cvecli/core/config.py
cvecli/models/__init__.py
cvecli/models/cve_model.py
cvecli/models/parquet_models.py
cvecli/models/query_filters.py
cvecli/services/__init__.py
cvecli/services/artifact_fetcher.py
cvecli/services/cpe.py
cvecli/services/downloader.py
cvecli/services/embeddings.py
cvecli/services/extractor.py
cvecli/services/search.py
cvecli/services/version.py
cvecli-0.1.1.data/data/share/cvecli/licences/CVE_TERMS_OF_USE.md
cvecli-0.1.1.data/data/share/cvecli/licences/NOTICE.txt
cvecli-0.1.1.dist-info/METADATA
cvecli-0.1.1.dist-info/WHEEL
cvecli-0.1.1.dist-info/entry_points.txt
cvecli-0.1.1.dist-info/licenses/LICENSE
cvecli-0.1.1.dist-info/RECORD
