Metadata-Version: 2.4
Name: cvecli
Version: 0.1.1
Summary: CLI tool for downloading, extracting, and searching CVE data
Project-URL: Homepage, https://github.com/RomainRiv/cvecli
Project-URL: Documentation, https://romainriv.github.io/cvecli/
Project-URL: Repository, https://github.com/RomainRiv/cvecli
Project-URL: Issues, https://github.com/RomainRiv/cvecli/issues
Project-URL: Changelog, https://github.com/RomainRiv/cvecli/releases
Author: Romain RIVIERE
License-Expression: MIT
License-File: LICENSE
Keywords: cli,cpe,cve,cwe,cybersecurity,nvd,security,vulnerability
Classifier: Development Status :: 4 - Beta
Classifier: Environment :: Console
Classifier: Intended Audience :: Developers
Classifier: Intended Audience :: Information Technology
Classifier: Intended Audience :: System Administrators
Classifier: License :: OSI Approved :: MIT License
Classifier: Operating System :: OS Independent
Classifier: Programming Language :: Python :: 3
Classifier: Programming Language :: Python :: 3.10
Classifier: Programming Language :: Python :: 3.11
Classifier: Programming Language :: Python :: 3.12
Classifier: Programming Language :: Python :: 3.13
Classifier: Topic :: Security
Classifier: Topic :: Utilities
Classifier: Typing :: Typed
Requires-Python: >=3.10
Requires-Dist: polars>=1.31.0
Requires-Dist: pydantic>=2.11.7
Requires-Dist: requests>=2.32.3
Requires-Dist: rich>=14.0.0
Requires-Dist: typer>=0.16.0
Requires-Dist: types-requests>=2.32.4.20250913
Provides-Extra: dev
Requires-Dist: black>=24.0.0; extra == 'dev'
Requires-Dist: datamodel-code-generator>=0.53.0; extra == 'dev'
Requires-Dist: fastembed>=0.5.0; extra == 'dev'
Requires-Dist: mypy>=1.8.0; extra == 'dev'
Requires-Dist: numpy>=2.0.0; extra == 'dev'
Requires-Dist: pytest-cov>=4.1.0; extra == 'dev'
Requires-Dist: pytest>=8.0.0; extra == 'dev'
Requires-Dist: types-requests>=2.32.4.20250611; extra == 'dev'
Provides-Extra: notebook
Requires-Dist: ipykernel>=6.29.0; extra == 'notebook'
Requires-Dist: jupyter>=1.0.0; extra == 'notebook'
Requires-Dist: plotly>=6.0.0; extra == 'notebook'
Provides-Extra: semantic
Requires-Dist: fastembed>=0.5.0; extra == 'semantic'
Requires-Dist: numpy>=2.0.0; extra == 'semantic'
